sigurd/__init__.py
sigurd/__pycache__/__init__.cpython-37.pyc
sigurd/nib_augsburg/README.md
sigurd/nib_augsburg/__init__.py
sigurd/nib_augsburg/line_annotated_nib_c.txt
sigurd/nib_augsburg/nib_a.txt
sigurd/nib_augsburg/nib_b.txt
sigurd/nib_augsburg/nib_c.txt
sigurd/nib_augsburg/nib_c.xml
sigurd/nib_augsburg/nib_n.txt
sigurd/nib_augsburg/nib_reader.py
sigurd/nib_augsburg/nib_reformat.py
sigurd/nib_augsburg/nib_retrieval.py
sigurd/nib_augsburg/nib_scripts.py
sigurd/nib_augsburg/nibelungen-extraction.ipynb
sigurd/nib_augsburg/.ipynb_checkpoints/nibelungen-extraction-checkpoint.ipynb
sigurd/nib_augsburg/__pycache__/__init__.cpython-37.pyc
sigurd/nib_augsburg/__pycache__/nib_reader.cpython-37.pyc
sigurd/nib_augsburg/__pycache__/nib_reformat.cpython-37.pyc
sigurd/nib_augsburg/__pycache__/nib_retrieval.cpython-37.pyc
sigurd/nib_augsburg/__pycache__/nib_scripts.cpython-37.pyc
sigurd/nib_augsburg/annotations/cities.txt
sigurd/nib_augsburg/annotations/names.txt
sigurd/nib_augsburg/annotations/peoples.txt
sigurd/nib_augsburg/annotations/places.txt
sigurd/nib_augsburg/annotations/regions_and_countries.txt
sigurd/nib_augsburg/annotations/rivers.txt
sigurd/nib_augsburg/extracted_nib_a/0.txt
sigurd/nib_augsburg/extracted_nib_a/1.txt
sigurd/nib_augsburg/extracted_nib_a/10.txt
sigurd/nib_augsburg/extracted_nib_a/11.txt
sigurd/nib_augsburg/extracted_nib_a/12.txt
sigurd/nib_augsburg/extracted_nib_a/13.txt
sigurd/nib_augsburg/extracted_nib_a/14.txt
sigurd/nib_augsburg/extracted_nib_a/15.txt
sigurd/nib_augsburg/extracted_nib_a/16.txt
sigurd/nib_augsburg/extracted_nib_a/17.txt
sigurd/nib_augsburg/extracted_nib_a/18.txt
sigurd/nib_augsburg/extracted_nib_a/19.txt
sigurd/nib_augsburg/extracted_nib_a/2.txt
sigurd/nib_augsburg/extracted_nib_a/20.txt
sigurd/nib_augsburg/extracted_nib_a/21.txt
sigurd/nib_augsburg/extracted_nib_a/22.txt
sigurd/nib_augsburg/extracted_nib_a/23.txt
sigurd/nib_augsburg/extracted_nib_a/24.txt
sigurd/nib_augsburg/extracted_nib_a/25.txt
sigurd-1.2.13.dist-info/LICENSE
sigurd-1.2.13.dist-info/METADATA
sigurd-1.2.13.dist-info/WHEEL
sigurd-1.2.13.dist-info/entry_points.txt
sigurd-1.2.13.dist-info/top_level.txt
sigurd-1.2.13.dist-info/zip-safe
sigurd-1.2.13.dist-info/RECORD
