Metadata-Version: 2.1
Name: sigurd
Version: 1.2.13
Summary: Code for presentation at Graz, 6th November 2019
Home-page: https://github.com/clemsciences/comparison_sigurdr_siegfried
Author: Clément Besnier
Author-email: clem@clementbesnier.fr
License: License :: OSI Approved :: MIT License
Keywords: old-norse,middle-high-german,siegfried,sigurdr
Platform: UNKNOWN
Classifier: Programming Language :: Python
Classifier: Programming Language :: Python :: 3
Classifier: Operating System :: OS Independent
Classifier: License :: OSI Approved :: MIT License
Classifier: Topic :: Text Processing
Classifier: Topic :: Text Processing :: Markup :: XML
Requires-Python: >=3.6
Requires-Dist: requests
Requires-Dist: PyPDF2
Requires-Dist: gensim
Requires-Dist: cltk (>=0.1.110)
Requires-Dist: bs4
Requires-Dist: lxml
Requires-Dist: nltk
Requires-Dist: norsecorpus (>=1.0.2)
Requires-Dist: jupyter
Requires-Dist: networkx
Requires-Dist: matplotlib
Requires-Dist: numpy
Requires-Dist: scikit-learn
Requires-Dist: pytest
